{
  "generated_at": "2025-11-22T08:53:36.867347+08:00",
  "total_titles_processed": 475,
  "failed_sources": [],
  "trends": [
    {
      "keyword_group": "科技 AI",
      "match_count": 22,
      "titles": [
        {
          "title": "英伟达内部会，黄仁勋坦言：太难了，“做得好是AI泡沫”，“一点点不及预期，整个世界就会崩溃”",
          "url": "https://wallstreetcn.com/articles/3759864",
          "source": "华尔街见闻",
          "ranks": [
            1
          ],
          "is_new": false,
          "appearance_count": 2,
          "time_info": "[02时17分 ~ 08时53分]"
        },
        {
          "title": "华为AI新技术揭晓！英伟达曾花50亿收购“同款”",
          "url": "https://www.cls.cn/detail/2207687",
          "source": "财联社热门",
          "ranks": [
            1
          ],
          "is_new": false,
          "appearance_count": 2,
          "time_info": "[02时17分 ~ 08时53分]"
        },
        {
          "title": "这26秒科技感直接拉满",
          "url": "https://s.weibo.com/weibo?q=%23%E8%BF%9926%E7%A7%92%E7%A7%91%E6%8A%80%E6%84%9F%E7%9B%B4%E6%8E%A5%E6%8B%89%E6%BB%A1%23&t=31&band_rank=3&Refer=top",
          "source": "微博",
          "ranks": [
            3
          ],
          "is_new": false,
          "appearance_count": 2,
          "time_info": "[02时17分 ~ 08时53分]"
        },
        {
          "title": "【早报】华为AI新技术揭晓；两家A股公司被证监会立案调查",
          "url": "https://www.cls.cn/detail/2207918",
          "source": "财联社热门",
          "ranks": [
            2
          ],
          "is_new": true,
          "appearance_count": 1,
          "time_info": "08时53分"
        },
        {
          "title": "硬科技再获增量资金加持！涉及AI、芯片等16只硬科技主题基金火速获批",
          "url": "https://www.cls.cn/detail/2207779",
          "source": "财联社热门",
          "ranks": [
            10,
            8
          ],
          "is_new": false,
          "appearance_count": 2,
          "time_info": "[02时17分 ~ 08时53分]"
        },
        {
          "title": "南向资金追踪｜逾百亿资金短线买入阿里 增仓科技股意愿强烈",
          "url": "https://www.cls.cn/detail/2207621",
          "source": "财联社热门",
          "ranks": [
            12,
            11
          ],
          "is_new": false,
          "appearance_count": 2,
          "time_info": "[02时17分 ~ 08时53分]"
        },
        {
          "title": "胡彦斌 不是AI的",
          "url": "https://s.weibo.com/weibo?q=%E8%83%A1%E5%BD%A6%E6%96%8C%20%E4%B8%8D%E6%98%AFAI%E7%9A%84&t=31&band_rank=21&Refer=top",
          "source": "微博",
          "ranks": [
            21
          ],
          "is_new": false,
          "appearance_count": 2,
          "time_info": "[02时17分 ~ 08时53分]"
        },
        {
          "title": "谷歌：将向美国大学生免费提供一年的Google AI Pro服务。",
          "url": "https://flash.jin10.com/detail/20251122020035429800",
          "source": "金十数据",
          "ranks": [
            6
          ],
          "is_new": false,
          "appearance_count": 1,
          "time_info": "02时17分"
        },
        {
          "title": "【焦点复盘】沪指放量长阴失守3900点，全市场超450股跌超7%，AI应用端一枝独秀",
          "url": "https://www.cls.cn/detail/2207484",
          "source": "财联社热门",
          "ranks": [
            7
          ],
          "is_new": false,
          "appearance_count": 1,
          "time_info": "02时17分"
        },
        {
          "title": "一文读懂大跌逻辑--高盛交易员“复盘”：美联储转鹰“拉开帷幕”，谷歌而非英伟达重塑“AI交易”，币圈重创散户，最终是“系统性抛售”",
          "url": "https://wallstreetcn.com/articles/3759889",
          "source": "华尔街见闻",
          "ranks": [
            8
          ],
          "is_new": true,
          "appearance_count": 1,
          "time_info": "08时53分"
        },
        {
          "title": "标普500指数的11个板块中，电信板块收涨2.15%，保健板块涨2.11%，原材料板块涨2.1%，可选消费板块涨1.74%，信息技术/科技板块涨0.07%表现倒数第二，公用事业板块大致收平。",
          "url": "https://wallstreetcn.com/livenews/3008933",
          "source": "华尔街见闻-快讯",
          "ranks": [
            8
          ],
          "is_new": true,
          "appearance_count": 1,
          "time_info": "08时53分"
        },
        {
          "title": "强得离谱！实测Nano Banana Pro：甚至不想叫它AI，这是视觉层面的AGI！",
          "url": "https://wallstreetcn.com/articles/3759838",
          "source": "华尔街见闻",
          "ranks": [
            9
          ],
          "is_new": false,
          "appearance_count": 1,
          "time_info": "02时17分"
        },
        {
          "title": "全球航空业ETF收涨3.5%，和银行业ETF领跑美股行业ETF，本周半导体ETF跌超5.4%、科技行业ETF累跌超5%",
          "url": "https://wallstreetcn.com/livenews/3008932",
          "source": "华尔街见闻-快讯",
          "ranks": [
            9
          ],
          "is_new": true,
          "appearance_count": 1,
          "time_info": "08时53分"
        },
        {
          "title": "AH股深度调整，创业板跌超3%，恒科指下跌1.8%，锂矿股领跌，AI应用逆势上涨，碳酸锂期货跌停",
          "url": "https://wallstreetcn.com/articles/3759852",
          "source": "华尔街见闻",
          "ranks": [
            10
          ],
          "is_new": true,
          "appearance_count": 1,
          "time_info": "08时53分"
        },
        {
          "title": "胡彦斌疑似承认恋情：接吻视频非AI",
          "url": "https://www.toutiao.com/trending/7575051643448741439/",
          "source": "今日头条",
          "ranks": [
            12
          ],
          "is_new": true,
          "appearance_count": 1,
          "time_info": "08时53分"
        },
        {
          "title": "谷歌推出BigQuery AI",
          "url": "https://wallstreetcn.com/livenews/3008826",
          "source": "华尔街见闻-快讯",
          "ranks": [
            15
          ],
          "is_new": false,
          "appearance_count": 1,
          "time_info": "02时17分"
        },
        {
          "title": "集体诉讼显示：Figma Inc.在训练自家人工智能（AI）模型方面并没有（事前）征求用户的意见。",
          "url": "https://wallstreetcn.com/livenews/3008923",
          "source": "华尔街见闻-快讯",
          "ranks": [
            15
          ],
          "is_new": true,
          "appearance_count": 1,
          "time_info": "08时53分"
        },
        {
          "title": "如何评价 Grok AI 被发现疑似设定强制吹捧马斯克身材和智力世界第一？",
          "url": "https://www.zhihu.com/question/1975115860181022671",
          "source": "知乎",
          "ranks": [
            18
          ],
          "is_new": false,
          "appearance_count": 1,
          "time_info": "02时17分"
        },
        {
          "title": "标普500指数涨幅扩大至1%，道指涨537点涨幅1.2%，纳指涨超0.7%，生物科技指数涨超2%，半导体指数涨超0.3%。",
          "url": "https://wallstreetcn.com/livenews/3008819",
          "source": "华尔街见闻-快讯",
          "ranks": [
            19
          ],
          "is_new": false,
          "appearance_count": 1,
          "time_info": "02时17分"
        },
        {
          "title": "如果 AI 能完美替代你现在的工作，那剩下的，什么是只有「人」才能做的事情？",
          "url": "https://www.zhihu.com/question/1971908267061019658",
          "source": "知乎",
          "ranks": [
            20
          ],
          "is_new": false,
          "appearance_count": 1,
          "time_info": "02时17分"
        },
        {
          "title": "胡彦斌回应亲吻照：不是AI",
          "url": "https://www.baidu.com/s?wd=%E8%83%A1%E5%BD%A6%E6%96%8C%E5%9B%9E%E5%BA%94%E4%BA%B2%E5%90%BB%E7%85%A7%EF%BC%9A%E4%B8%8D%E6%98%AFAI",
          "source": "百度热搜",
          "ranks": [
            23
          ],
          "is_new": true,
          "appearance_count": 1,
          "time_info": "08时53分"
        },
        {
          "title": "谷歌：我们推出BigQuery AI。",
          "url": "https://flash.jin10.com/detail/20251122011317548800",
          "source": "金十数据",
          "ranks": [
            23
          ],
          "is_new": false,
          "appearance_count": 1,
          "time_info": "02时17分"
        }
      ]
    },
    {
      "keyword_group": "经济",
      "match_count": 7,
      "titles": [
        {
          "title": "日本多个行业为高市早苗买单，50 多万名中国游客取消原定日本行程，此次事件对日本经济影响到底有多大？",
          "url": "https://www.zhihu.com/question/1975169592130286012",
          "source": "知乎",
          "ranks": [
            2
          ],
          "is_new": false,
          "appearance_count": 2,
          "time_info": "[02时17分 ~ 08时53分]"
        },
        {
          "title": "【美国四分之一失业者拥有本科或以上学历，创纪录水平】9月，美国25岁及以上、拥有至少本科学历的失业人口超过190万人，占全美失业总人数的四分之一。自1992年有数据记录以来，这一比例在2025年之前从未达到如此之高。摩根大通美国首席经济学家Michael Feroli指出，受过大学教育的人群失业率上升“应该会进一步加剧对人工智能引发失业的担忧”。与此同时，一系列大型企业宣布裁员，包括亚马逊、塔吉特和星巴克。就业服务公司Challenger, Gray & Christmas的最新报告显示，随着人工智能重塑行业格局以及成本削减加速，美国企业10月份宣布的裁员规模是二十多年来同期最高水平。",
          "url": "https://wallstreetcn.com/livenews/3008845",
          "source": "华尔街见闻-快讯",
          "ranks": [
            2
          ],
          "is_new": false,
          "appearance_count": 1,
          "time_info": "02时17分"
        },
        {
          "title": "与中国闹翻日本经济界先慌了",
          "url": "https://www.toutiao.com/trending/7574250888475590692/",
          "source": "今日头条",
          "ranks": [
            6
          ],
          "is_new": false,
          "appearance_count": 1,
          "time_info": "02时17分"
        },
        {
          "title": "疫情以来最大规模！日本批准21.3万亿日元经济刺激计划",
          "url": "https://wallstreetcn.com/articles/3759861",
          "source": "华尔街见闻",
          "ranks": [
            9
          ],
          "is_new": true,
          "appearance_count": 1,
          "time_info": "08时53分"
        },
        {
          "title": "法国游戏公司育碧娱乐（UbiSoft）：腾讯控股对Vantage Studios完成11.6亿欧元投资。 腾讯对其有26.32%的经济利益。",
          "url": "https://wallstreetcn.com/livenews/3008817",
          "source": "华尔街见闻-快讯",
          "ranks": [
            20
          ],
          "is_new": false,
          "appearance_count": 1,
          "time_info": "02时17分"
        },
        {
          "title": "日本学者：高市言论冲击日本经济",
          "url": "https://www.douyin.com/hot/2312966",
          "source": "抖音",
          "ranks": [
            21
          ],
          "is_new": true,
          "appearance_count": 1,
          "time_info": "08时53分"
        },
        {
          "title": "房利美发布2025年11月经济与住房展望。",
          "url": "https://flash.jin10.com/detail/20251122030029864800",
          "source": "金十数据",
          "ranks": [
            26
          ],
          "is_new": true,
          "appearance_count": 1,
          "time_info": "08时53分"
        }
      ]
    }
  ],
  "report_image_url": "https://ysayle-ai.github.io/ysayle-ainews.github.io/img/news.jpg"
}